aicrowd_gym/__init__.py
aicrowd_gym/make.py
aicrowd_gym/version.py
aicrowd_gym-0.0.3.dist-info/METADATA
aicrowd_gym-0.0.3.dist-info/WHEEL
aicrowd_gym-0.0.3.dist-info/top_level.txt
aicrowd_gym-0.0.3.dist-info/RECORD
